pydmoo/__init__.py
pydmoo/algorithms/__init__.py
pydmoo/algorithms/base/__init__.py
pydmoo/algorithms/base/core/__init__.py
pydmoo/algorithms/base/core/algorithm.py
pydmoo/algorithms/base/core/genetic.py
pydmoo/algorithms/base/dmoo/__init__.py
pydmoo/algorithms/base/dmoo/dmoead.py
pydmoo/algorithms/base/dmoo/dmoeadde.py
pydmoo/algorithms/base/dmoo/dmopso.py
pydmoo/algorithms/base/dmoo/dnsga2.py
pydmoo/algorithms/base/moo/__init__.py
pydmoo/algorithms/base/moo/moead.py
pydmoo/algorithms/base/moo/moeadde.py
pydmoo/algorithms/base/moo/mopso.py
pydmoo/algorithms/base/moo/nsga2.py
pydmoo/algorithms/classic/__init__.py
pydmoo/algorithms/classic/moead_ae.py
pydmoo/algorithms/classic/moead_pps.py
pydmoo/algorithms/classic/moead_svr.py
pydmoo/algorithms/classic/moeadde_ae.py
pydmoo/algorithms/classic/moeadde_pps.py
pydmoo/algorithms/classic/moeadde_svr.py
pydmoo/algorithms/classic/nsga2_ae.py
pydmoo/algorithms/classic/nsga2_pps.py
pydmoo/algorithms/knowledge/moead_ktmm.py
pydmoo/algorithms/knowledge/moeadde_ktmm.py
pydmoo/algorithms/knowledge/nsga2_ktmm.py
pydmoo/algorithms/learning/__init__.py
pydmoo/algorithms/learning/moead_tr.py
pydmoo/algorithms/learning/moeadde_tr.py
pydmoo/algorithms/learning/nsga2_tr.py
pydmoo/algorithms/modern/__init__.py
pydmoo/algorithms/modern/moead_imkt.py
pydmoo/algorithms/modern/moead_imkt_igp.py
pydmoo/algorithms/modern/moead_imkt_lstm.py
pydmoo/algorithms/modern/moead_imkt_n.py
pydmoo/algorithms/modern/moead_imkt_n_igp.py
pydmoo/algorithms/modern/moead_imkt_n_lstm.py
pydmoo/algorithms/modern/moead_ktmm.py
pydmoo/algorithms/modern/moeadde_imkt.py
pydmoo/algorithms/modern/moeadde_imkt_clstm.py
pydmoo/algorithms/modern/moeadde_imkt_igp.py
pydmoo/algorithms/modern/moeadde_imkt_lstm.py
pydmoo/algorithms/modern/moeadde_imkt_n.py
pydmoo/algorithms/modern/moeadde_imkt_n_clstm.py
pydmoo/algorithms/modern/moeadde_imkt_n_igp.py
pydmoo/algorithms/modern/moeadde_imkt_n_lstm.py
pydmoo/algorithms/modern/moeadde_ktmm.py
pydmoo-0.1.4.dist-info/METADATA
pydmoo-0.1.4.dist-info/WHEEL
pydmoo-0.1.4.dist-info/licenses/LICENSE
pydmoo-0.1.4.dist-info/RECORD
